{
  "parent": "minecraft:recipes/root",
  "criteria": {
    "has_bone_setts": {
      "conditions": {
        "items": [
          {
            "items": [
              "perit:bone_setts"
            ]
          }
        ]
      },
      "trigger": "minecraft:inventory_changed"
    },
    "has_the_recipe": {
      "conditions": {
        "recipe": "minecraft:bone_sett_wall_from_bone_setts_stonecutting"
      },
      "trigger": "minecraft:recipe_unlocked"
    }
  },
  "requirements": [
    [
      "has_bone_setts",
      "has_the_recipe"
    ]
  ],
  "rewards": {
    "recipes": [
      "minecraft:bone_sett_wall_from_bone_setts_stonecutting"
    ]
  }
}